bctl/__init__.py
bctl/client.py
bctl/common.py
bctl/config.py
bctl/daemon.py
bctl/debouncer.py
bctl/display.py
bctl/exceptions.py
bctl/notify.py
bctl/udev_monitor.py
bctl/bin/__init__.py
bctl/bin/main_client.py
bctl/bin/main_daemon.py
bctl/bin/main_daemon_sim.py
bctl-0.0.6.dist-info/METADATA
bctl-0.0.6.dist-info/WHEEL
bctl-0.0.6.dist-info/entry_points.txt
bctl-0.0.6.dist-info/top_level.txt
bctl-0.0.6.dist-info/RECORD
