Metadata-Version: 2.4
Name: bctl
Version: 0.0.6
Summary: service for controlling brightness of laptop & external displays
License-Expression: MIT
Project-URL: homepage, https://github.com/haridusministeerium/bctl
Project-URL: issues, https://github.com/haridusministeerium/bctl/issues
Project-URL: changelog, https://github.com/haridusministeerium/bctl/blob/master/CHANGELOG.md
Keywords: brightness,brightness-control,display-brightness,screen-brightness
Classifier: Development Status :: 5 - Production/Stable
Classifier: Intended Audience :: End Users/Desktop
Classifier: Topic :: System :: Hardware
Classifier: Programming Language :: Python :: 3
Classifier: Operating System :: POSIX :: Linux
Requires-Python: >=3.12
Requires-Dist: click
Requires-Dist: tendo
Requires-Dist: aiofiles
Requires-Dist: pyudev
Requires-Dist: desktop-notify
Requires-Dist: pydantic
Requires-Dist: pydash
Requires-Dist: retry-deco
Requires-Dist: dbus-next
Provides-Extra: dev
Requires-Dist: ruff; extra == "dev"
Requires-Dist: ty; extra == "dev"
Requires-Dist: ipdb; extra == "dev"
